{"P21": {"labels": ["\u90e8\u7f72"], "postTitle": "Shiny-Apps", "postUrl": "post/Shiny-Apps.html", "createdDate": "2024-04-27", "dateLabelColor": "#bc4c00"}, "P20": {"labels": ["\u96c6\u8bad"], "postTitle": "T3-common online tools", "postUrl": "post/T3-common%20online%20tools.html", "createdDate": "2024-04-11", "dateLabelColor": "#bc4c00"}, "P19": {"labels": ["\u96c6\u8bad"], "postTitle": "T2-snakemake", "postUrl": "post/T2-snakemake.html", "createdDate": "2024-03-03", "dateLabelColor": "#bc4c00"}, "P18": {"labels": ["\u96c6\u8bad"], "postTitle": "T1-Unix\u57fa\u672c\u64cd\u4f5c\u4e0eggplot\u53ef\u89c6\u5316\u6982\u89c8", "postUrl": "post/T1-Unix-ji-ben-cao-zuo-yu-ggplot-ke-shi-hua-gai-lan.html", "createdDate": "2024-01-16", "dateLabelColor": "#bc4c00"}, "P17": {"labels": ["\u516c\u544a"], "postTitle": "TCCIA\u6210\u679c\u53d1\u5e03\u4e0e\u6210\u5458\u62db\u52df", "postUrl": "post/TCCIA-cheng-guo-fa-bu-yu-cheng-yuan-zhao-mu.html", "createdDate": "2024-01-12", "dateLabelColor": "#bc4c00"}, "P16": {"labels": ["\u8fd0\u7ef4"], "postTitle": "\u670d\u52a1\u5668\u6295\u9012CircRNA\u8ba1\u7b97\u4efb\u52a1\u6559\u7a0b", "postUrl": "post/fu-wu-qi-tou-di-CircRNA-ji-suan-ren-wu-jiao-cheng.html", "createdDate": "2024-01-07", "dateLabelColor": "#bc4c00"}, "P15": {"labels": ["\u96c6\u8bad"], "postTitle": "T0-R\u4e0eShiny", "postUrl": "post/T0-R-yu-Shiny.html", "createdDate": "2024-01-07", "dateLabelColor": "#bc4c00"}, "P13": {"labels": ["Web\u5f00\u53d1"], "postTitle": "\u7f51\u9875\u8def\u7531\u548cshiny.router\u4f7f\u7528\u65b9\u6cd5", "postUrl": "post/wang-ye-lu-you-he-shiny.router-shi-yong-fang-fa.html", "createdDate": "2023-12-18", "dateLabelColor": "#A333D0"}, "P10": {"labels": ["\u8fd0\u7ef4"], "postTitle": "shiny-server\u5b89\u88c5\u548c\u914d\u7f6e", "postUrl": "post/shiny-server-an-zhuang-he-pei-zhi.html", "createdDate": "2023-12-09", "dateLabelColor": "#A333D0"}, "P9": {"labels": ["\u5b66\u4e60"], "postTitle": "Web\u4e13\u4e1a\u5f00\u53d1\u5b66\u4e60\u8def\u5f84", "postUrl": "post/Web-zhuan-ye-kai-fa-xue-xi-lu-jing.html", "createdDate": "2023-12-08", "dateLabelColor": "#A333D0"}, "P8": {"labels": ["\u8fd0\u7ef4"], "postTitle": "shiny\u5e94\u7528\u7684nginx\u914d\u7f6e", "postUrl": "post/shiny-ying-yong-de-nginx-pei-zhi.html", "createdDate": "2023-12-07", "dateLabelColor": "#A333D0"}, "P7": {"labels": ["\u5e73\u53f0"], "postTitle": "\u56e2\u961f\u8d44\u6e90\u5217\u8868", "postUrl": "post/tuan-dui-zi-yuan-lie-biao.html", "createdDate": "2023-12-07", "dateLabelColor": "#A333D0"}, "P6": {"labels": ["\u516c\u544a"], "postTitle": "\u9879\u76ee\u6210\u679c\u5217\u8868", "postUrl": "post/xiang-mu-cheng-guo-lie-biao.html", "createdDate": "2023-12-06", "dateLabelColor": "#A333D0"}, "P5": {"labels": ["\u516c\u544a"], "postTitle": "\u56e2\u961f\u67b6\u6784", "postUrl": "post/tuan-dui-jia-gou.html", "createdDate": "2023-12-06", "dateLabelColor": "#A333D0"}, "P4": {"labels": ["outdate"], "postTitle": "\u90e8\u7f72zhoulab.ac.cn\u9875\u9762", "postUrl": "post/bu-shu-zhoulab.ac.cn-ye-mian.html", "createdDate": "2023-12-06", "dateLabelColor": "#A333D0"}, "P3": {"labels": ["\u516c\u544a"], "postTitle": "\u535a\u5ba2\u4f7f\u7528\u8bf4\u660e", "postUrl": "post/bo-ke-shi-yong-shuo-ming.html", "createdDate": "2023-12-01", "dateLabelColor": "#A333D0"}, "labelColorDict": {"about": "#FC9D81", "bug": "#d73a4a", "documentation": "#0075ca", "duplicate": "#cfd3d7", "enhancement": "#a2eeef", "good first issue": "#7057ff", "help wanted": "#008672", "invalid": "#e4e669", "outdate": "#3E2E58", "question": "#d876e3", "Team": "#696913", "Web\u5f00\u53d1": "#7E86F9", "wontfix": "#ffffff", "\u516c\u544a": "#98A8FA", "\u5b66\u4e60": "#C31D0B", "\u5e73\u53f0": "#A8E5E5", "\u8fd0\u7ef4": "#479AD1", "\u90e8\u7f72": "#73BF77", "\u96c6\u8bad": "#2EB934"}}